dowy/__init__.py
dowy/command_line.py
dowy-0.6.dist-info/LICENSE.txt
dowy-0.6.dist-info/METADATA
dowy-0.6.dist-info/WHEEL
dowy-0.6.dist-info/entry_points.txt
dowy-0.6.dist-info/top_level.txt
dowy-0.6.dist-info/RECORD
