Metadata-Version: 2.1
Name: dowy
Version: 0.6
Summary: YouTube CLI 4K downloader for Windows
Home-page: https://github.com/BestCactus/yt-4k-downloader
Download-URL: https://pypi.org/project/dowy/
Author: Vojtěch Fluger
Author-email: vojtech.fluger@gmail.com
License: MIT License
License-File: LICENSE.txt
Requires-Dist: pytubefix
Requires-Dist: python-ffmpeg
Requires-Dist: userpaths
Requires-Dist: pywin32
Requires-Dist: tabulate
